<?xml version="1.0" encoding="UTF-8"?>
<beans xmlns="http://www.springframework.org/schema/beans"
       xmlns:xsi="http://www.w3.org/2001/XMLSchema-instance"
       xsi:schemaLocation="http://www.springframework.org/schema/beans http://www.springframework.org/schema/beans/spring-beans.xsd">

    <bean class="com.mchange.v2.c3p0.ComboPooledDataSource" id="dataSource">
        <property name="driverClass" value=""/>
        <property name="jdbcUrl" value=""/>
        <property name="user" value=""/>
        <property name="password" value=""/>
        <property name="minPoolSize" value=""/>
        <property name="maxPoolSize" value=""/>
        <property name="acquireIncrement" value=""/>
    </bean>

    <bean class="org.springframework.beans.factory.config.PropertyPlaceholderConfigurer">
        <property name="location" value="classpath:jdbc.properties"/>
    </bean>

</beans>